funpack/__init__.py
funpack/__main__.py
funpack/cleaning.py
funpack/cleaning_functions.py
funpack/config.py
funpack/custom.py
funpack/datatable.py
funpack/dryrun.py
funpack/exporting.py
funpack/exporting_hdf5.py
funpack/exporting_tsv.py
funpack/fileinfo.py
funpack/icd10.py
funpack/loadtables.py
funpack/main.py
funpack/merging.py
funpack/metaproc_functions.py
funpack/processing.py
funpack/processing_functions.py
funpack/processing_functions_core.py
funpack/util.py
funpack/configs/README
funpack/importing/__init__.py
funpack/importing/core.py
funpack/importing/filter.py
funpack/importing/reindex.py
funpack/parsing/__init__.py
funpack/parsing/process.py
funpack/parsing/value_expression.py
funpack/parsing/variable_expression.py
funpack/plugins/fmrib.py
funpack/schema/README.txt
funpack/schema/__init__.py
funpack/schema/coding.py
funpack/schema/encoding.txt
funpack/schema/field.txt
funpack/schema/hierarchy.py
funpack/schema/type.txt
funpack/schema/coding/coding100605.tsv
funpack/schema/coding/coding100629.tsv
funpack/schema/coding/coding4.tsv
funpack/schema/coding/coding744.tsv
funpack/schema/hierarchy/coding1001.tsv
funpack/schema/hierarchy/coding1003.tsv
funpack/schema/hierarchy/coding1005.tsv
funpack/schema/hierarchy/coding1006.tsv
funpack/schema/hierarchy/coding19.tsv
funpack/schema/hierarchy/coding2.tsv
funpack/schema/hierarchy/coding22000.tsv
funpack/schema/hierarchy/coding240.tsv
funpack/schema/hierarchy/coding259.tsv
funpack/schema/hierarchy/coding264.tsv
funpack/schema/hierarchy/coding265.tsv
funpack/schema/hierarchy/coding266.tsv
funpack/schema/hierarchy/coding267.tsv
funpack/schema/hierarchy/coding268.tsv
funpack/schema/hierarchy/coding3.tsv
funpack/schema/hierarchy/coding38.tsv
funpack/schema/hierarchy/coding39.tsv
funpack/schema/hierarchy/coding47.tsv
funpack/schema/hierarchy/coding49.tsv
funpack/schema/hierarchy/coding497.tsv
funpack/schema/hierarchy/coding5.tsv
funpack/schema/hierarchy/coding50.tsv
funpack/schema/hierarchy/coding51.tsv
fmrib_unpack-3.8.1.dist-info/LICENSE
fmrib_unpack-3.8.1.dist-info/METADATA
fmrib_unpack-3.8.1.dist-info/WHEEL
fmrib_unpack-3.8.1.dist-info/entry_points.txt
fmrib_unpack-3.8.1.dist-info/top_level.txt
fmrib_unpack-3.8.1.dist-info/RECORD
