Metadata-Version: 2.1
Name: fmrib-unpack
Version: 3.8.1
Summary: The FMRIB UKBiobank Normalisation, Parsing And Cleaning Kit
Author-email: Paul McCarthy <paul.mccarthy@ndcn.ox.ac.uk>, Thomas Nichols <tom.nichols@bdi.ox.ac.uk>, Jessie Liu <Zhangdaihong.Liu@warwick.ac.uk>, Steve Smith <steve@fmrib.ox.ac.uk>
License: Apache License Version 2.0
Project-URL: Repository, https://git.fmrib.ox.ac.uk/fsl/funpack.git
Project-URL: Documentation, https://open.win.ox.ac.uk/pages/fsl/funpack/
Requires-Python: >=3.8
License-File: LICENSE
Requires-Dist: fmrib-unpack-fmrib-config
Requires-Dist: h5py
Requires-Dist: numpy
Requires-Dist: pandas >=0.24
Requires-Dist: pyparsing
Requires-Dist: tables
Requires-Dist: threadpoolctl
Requires-Dist: typing-extensions
Provides-Extra: demo
Requires-Dist: bash-kernel ; extra == 'demo'
Requires-Dist: jupyter ; extra == 'demo'
Requires-Dist: nbclassic ; extra == 'demo'
Requires-Dist: notebook ; extra == 'demo'
Requires-Dist: pygments ; extra == 'demo'
Provides-Extra: test
Requires-Dist: coverage ; extra == 'test'
Requires-Dist: pytest ; extra == 'test'
Requires-Dist: pytest-cov ; extra == 'test'
Requires-Dist: jinja2 ; extra == 'test'
Requires-Dist: jupyter-server ; extra == 'test'
Requires-Dist: notedown ; extra == 'test'
Requires-Dist: nbconvert ; extra == 'test'
Requires-Dist: sphinx ; extra == 'test'
Requires-Dist: sphinx-rtd-theme ; extra == 'test'
Requires-Dist: nbsphinx ; extra == 'test'
Requires-Dist: pylint ; extra == 'test'
Requires-Dist: flake8 ; extra == 'test'
